craftr/__init__.py
craftr/core/__init__.py
craftr/core/configurable.py
craftr/core/error.py
craftr/core/py.typed
craftr/core/settings.py
craftr/core/actions/__init__.py
craftr/core/actions/action.py
craftr/core/actions/command_action.py
craftr/core/actions/create_directory_action.py
craftr/core/actions/lambda_action.py
craftr/core/actions/write_file_action.py
craftr/core/context/__init__.py
craftr/core/executor/__init__.py
craftr/core/executor/api.py
craftr/core/executor/default.py
craftr/core/executor/graph.py
craftr/core/plugin/__init__.py
craftr/core/plugin/api.py
craftr/core/plugin/default.py
craftr/core/project/__init__.py
craftr/core/project/project.py
craftr/core/project/loader/__init__.py
craftr/core/project/loader/api.py
craftr/core/project/loader/default.py
craftr/core/project/loader/delegate.py
craftr/core/property/__init__.py
craftr/core/property/property.py
craftr/core/property/provider.py
craftr/core/property/typechecking.py
craftr/core/task/__init__.py
craftr/core/task/state.py
craftr/core/task/task.py
craftr/core/task/selector/__init__.py
craftr/core/task/selector/api.py
craftr/core/task/selector/default.py
craftr/core/util/__init__.py
craftr/core/util/caching.py
craftr/core/util/collections.py
craftr/core/util/pyimport.py
craftr/core/util/typing.py
craftr/core/util/weak.py
craftr_core-0.2.2.dist-info/METADATA
craftr_core-0.2.2.dist-info/WHEEL
craftr_core-0.2.2.dist-info/top_level.txt
craftr_core-0.2.2.dist-info/RECORD
