Metadata-Version: 2.1
Name: craftr-core
Version: 0.2.2
Summary: The core framework for the Craftr build system.
Home-page: UNKNOWN
Author: Niklas Rosenstein
Author-email: rosensteinniklas@gmail.com
License: UNKNOWN
Platform: UNKNOWN
Requires-Python: >=3.8.0,<4.0.0
Requires-Dist: nr.caching (<1.0.0,>=0.3.2)
Requires-Dist: nr.preconditions (<1.0.0,>=0.0.4)
Requires-Dist: typing-extensions (<4.0.0,>=3.10.0.0)
Provides-Extra: test
Requires-Dist: types-setuptools ; extra == 'test'
Requires-Dist: types-termcolor ; extra == 'test'
